menu/__init__.py
menu/_version.py
menu/admin.py
menu/apps.py
menu/auto_insert_group.py
menu/menus.py
menu/models.py
menu/tests.py
menu/urls.py
menu/views.py
menu/migrations/0001_initial.py
menu/migrations/0002_menugroup_kind.py
menu/migrations/0003_menu_is_new_alter_menu_link.py
menu/migrations/0004_alter_menu_menu_group.py
menu/migrations/0005_remove_menugroup_site_menugroup_group_and_more.py
menu/migrations/0006_alter_menugrouptranslation_unique_together_and_more.py
menu/migrations/0007_auto_20230130_1141.py
menu/migrations/0008_menu_exclude_menu.py
menu/migrations/__init__.py
menu/static/css/main.css
menu/static/fonts/iconic/css/material-design-iconic-font.css
menu/static/fonts/iconic/css/material-design-iconic-font.min.css
menu/static/fonts/iconic/fonts/Material-Design-Iconic-Font.eot
menu/static/fonts/iconic/fonts/Material-Design-Iconic-Font.svg
menu/static/fonts/iconic/fonts/Material-Design-Iconic-Font.ttf
menu/static/fonts/iconic/fonts/Material-Design-Iconic-Font.woff
menu/static/fonts/iconic/fonts/Material-Design-Iconic-Font.woff2
menu/static/parler/admin/parler_admin.css
menu/static/vendor/bootstrap/css/bootstrap-grid.css
menu/static/vendor/bootstrap/css/bootstrap-grid.css.map
menu/static/vendor/bootstrap/css/bootstrap-grid.min.css
menu/static/vendor/bootstrap/css/bootstrap-grid.min.css.map
menu/static/vendor/bootstrap/css/bootstrap-reboot.css
menu/static/vendor/bootstrap/css/bootstrap-reboot.css.map
menu/static/vendor/bootstrap/css/bootstrap-reboot.min.css
menu/static/vendor/bootstrap/css/bootstrap-reboot.min.css.map
menu/static/vendor/bootstrap/css/bootstrap.css
menu/static/vendor/bootstrap/css/bootstrap.css.map
menu/static/vendor/bootstrap/css/bootstrap.min.css
menu/static/vendor/bootstrap/css/bootstrap.min.css.map
menu/static/vendor/bootstrap/js/bootstrap.js
menu/static/vendor/bootstrap/js/bootstrap.min.js
menu/static/vendor/bootstrap/js/popper.js
menu/static/vendor/bootstrap/js/popper.min.js
menu/static/vendor/bootstrap/js/tooltip.js
django_outbox_menu-1.1.30.dist-info/LICENSE
django_outbox_menu-1.1.30.dist-info/METADATA
django_outbox_menu-1.1.30.dist-info/WHEEL
django_outbox_menu-1.1.30.dist-info/top_level.txt
django_outbox_menu-1.1.30.dist-info/RECORD
