Metadata-Version: 2.1
Name: django-outbox-menu
Version: 1.1.30
Summary: DJANGO OUTBOX MENU
Home-page: https://github.com/PROJECT-OUTBOX/django_lib_outbox_menu.git
Author-email: suratiwan03@gmail.com
Keywords: menu,model base,environment,django
Classifier: License :: OSI Approved :: BSD License
Classifier: Intended Audience :: Developers
Classifier: Programming Language :: Python :: 3 :: Only
License-File: LICENSE
Requires-Dist: django-parler
